gohighlevel/__init__.py
gohighlevel/main.py
gohighlevel/classes/__init__.py
gohighlevel/classes/blogs.py
gohighlevel/classes/business.py
gohighlevel/classes/calendars.py
gohighlevel/classes/calendars_appointmentsnotes.py
gohighlevel/classes/calendars_events.py
gohighlevel/classes/calendars_groups.py
gohighlevel/classes/calendars_notifications.py
gohighlevel/classes/calendars_resources.py
gohighlevel/classes/campaigns.py
gohighlevel/classes/company.py
gohighlevel/classes/contacts.py
gohighlevel/classes/contacts_appointments.py
gohighlevel/classes/contacts_campaigns.py
gohighlevel/classes/contacts_notes.py
gohighlevel/classes/contacts_tags.py
gohighlevel/classes/contacts_tasks.py
gohighlevel/classes/contacts_workflows.py
gohighlevel/classes/conversations.py
gohighlevel/classes/conversations_email.py
gohighlevel/classes/conversations_messages.py
gohighlevel/classes/conversations_providers.py
gohighlevel/classes/courses.py
gohighlevel/classes/customfields.py
gohighlevel/classes/custommenus.py
gohighlevel/classes/email.py
gohighlevel/classes/forms.py
gohighlevel/classes/funnels.py
gohighlevel/classes/funnels_redirect.py
gohighlevel/classes/location.py
gohighlevel/classes/medialibrary.py
gohighlevel/classes/oauth.py
gohighlevel/classes/opportunities.py
gohighlevel/classes/opportunities_notes.py
gohighlevel/classes/opportunities_pipelines.py
gohighlevel/classes/payments.py
gohighlevel/classes/payments_coupons.py
gohighlevel/classes/payments_customproviders.py
gohighlevel/classes/payments_integrations.py
gohighlevel/classes/payments_orderfulfillments.py
gohighlevel/classes/payments_orders.py
gohighlevel/classes/payments_subscriptions.py
gohighlevel/classes/payments_transactions.py
gohighlevel/classes/products.py
gohighlevel/classes/products_prices.py
gohighlevel/classes/saas.py
gohighlevel/classes/snapshots.py
gohighlevel/classes/subaccounts.py
gohighlevel/classes/subaccounts_customfields.py
gohighlevel/classes/subaccounts_customvalues.py
gohighlevel/classes/surveys.py
gohighlevel-1.0.2.dist-info/METADATA
gohighlevel-1.0.2.dist-info/WHEEL
gohighlevel-1.0.2.dist-info/licenses/LICENSE
gohighlevel-1.0.2.dist-info/RECORD
