Metadata-Version: 2.4
Name: gohighlevel
Version: 1.0.2
Summary: Go Highlevel Python ease of use library implementation to their API
Project-URL: Homepage, https://github.com/M2KDevelopments/gohighlevel-py
Project-URL: Issues, https://github.com/M2KDevelopments/gohighlevel-py/issues
Author-email: M2K Developments <m2kdevelopments@gmail.com>
License-File: LICENSE
Classifier: License :: OSI Approved :: MIT License
Classifier: Operating System :: OS Independent
Classifier: Programming Language :: Python :: 3
Requires-Python: >=3.0
Requires-Dist: requests
Requires-Dist: typing-extensions
